Metadata-Version: 2.1
Name: plprofiler-client
Version: 4.2
Summary: PL/pgSQL Profiler module and command line tool
Home-page: https://github.com/bigsql/plprofiler
Author: Jan Wieck
Author-email: jan@wi3ck.info
License: Artistic License and CDDL
Platform: UNKNOWN
